CHANGELOG.rst
LICENSE.txt
MANIFEST.in
README.rst
setup.py
bin/fypp
src/fypp.py
src/fypp.egg-info/PKG-INFO
src/fypp.egg-info/SOURCES.txt
src/fypp.egg-info/dependency_links.txt
src/fypp.egg-info/entry_points.txt
src/fypp.egg-info/top_level.txt
test/inimod.py
test/inimod2.py
test/runtests.sh
test/test_fypp.py
test/include/assert.inc
test/include/failingmacro.inc
test/include/fypp1.inc
test/include/inimod2.py
test/include/subfolder/fypp2.inc
test/include/subfolder/include_fypp1.inc
test/include/subfolder/include_fypp2.inc